Metadata-Version: 2.1
Name: fast_norm_cuda
Version: 0.2.0
Summary: A fast, yet specialized, RMSNorm/LayerNorm implementation
Home-page: https://github.com/yuantailing/fast-norm-cuda
Author: Tailing Yuan
Author-email: yuantailing@gmail.com
License: MIT
Classifier: Development Status :: 3 - Alpha
Classifier: Environment :: GPU :: NVIDIA CUDA
Classifier: Programming Language :: Python :: 3
Classifier: Intended Audience :: Developers
Classifier: License :: OSI Approved :: MIT License
Classifier: Topic :: Software Development :: Libraries :: Python Modules
Requires-Python: >=3.3
License-File: LICENSE
